odoo/addons/product_analytic_sale/README.rst
odoo/addons/product_analytic_sale/__init__.py
odoo/addons/product_analytic_sale/__manifest__.py
odoo/addons/product_analytic_sale/i18n/it.po
odoo/addons/product_analytic_sale/i18n/product_analytic_sale.pot
odoo/addons/product_analytic_sale/i18n/sv.po
odoo/addons/product_analytic_sale/models/__init__.py
odoo/addons/product_analytic_sale/models/sale_order_line.py
odoo/addons/product_analytic_sale/readme/CONTRIBUTORS.rst
odoo/addons/product_analytic_sale/readme/DESCRIPTION.rst
odoo/addons/product_analytic_sale/static/description/icon.png
odoo/addons/product_analytic_sale/static/description/index.html
odoo/addons/product_analytic_sale/wizards/__init__.py
odoo/addons/product_analytic_sale/wizards/sale_advance_payment_inv.py
odoo14_addon_product_analytic_sale-14.0.1.0.1.dev10.dist-info/METADATA
odoo14_addon_product_analytic_sale-14.0.1.0.1.dev10.dist-info/WHEEL
odoo14_addon_product_analytic_sale-14.0.1.0.1.dev10.dist-info/top_level.txt
odoo14_addon_product_analytic_sale-14.0.1.0.1.dev10.dist-info/RECORD
