Metadata-Version: 2.1
Name: odoo14-addon-product_analytic_sale
Version: 14.0.1.0.1.dev10
Summary: Glue module between sale and product_analytic
Home-page: https://github.com/OCA/account-analytic
Author: Akretion,Odoo Community Association (OCA)
Author-email: support@odoo-community.org
License: AGPL-3
Classifier: Programming Language :: Python
Classifier: Framework :: Odoo
Classifier: Framework :: Odoo :: 14.0
Classifier: License :: OSI Approved :: GNU Affero General Public License v3
Requires-Python: >=3.6
Requires-Dist: odoo14-addon-product-analytic
Requires-Dist: odoo<14.1dev,>=14.0a
